{
  "version": "7",
  "dialect": "postgresql",
  "entries": [
    {
      "idx": 0,
      "version": "7",
      "when": 1776465772646,
      "tag": "0000_initial",
      "breakpoints": true
    },
    {
      "idx": 1,
      "version": "7",
      "when": 1776466276654,
      "tag": "0001_auth",
      "breakpoints": true
    },
    {
      "idx": 2,
      "version": "7",
      "when": 1776507752738,
      "tag": "0002_permissions",
      "breakpoints": true
    },
    {
      "idx": 3,
      "version": "7",
      "when": 1776508403280,
      "tag": "0003_phase1_org_backbone",
      "breakpoints": true
    },
    {
      "idx": 4,
      "version": "7",
      "when": 1776517799666,
      "tag": "0004_phase2_templates_inspections",
      "breakpoints": true
    },
    {
      "idx": 5,
      "version": "7",
      "when": 1776533428652,
      "tag": "0005_phase2_inspections",
      "breakpoints": true
    }
  ]
}
